Metadata-Version: 2.4
Name: iflow-mcp_minhyeoky_ledger
Version: 0.1.0
Summary: A Model Context Protocol server providing tools to execute Ledger, a powerful command-line accounting system, commands.
Author-email: Minhyeok Lee <minhyeok.lee95@gmail.com>
License-Expression: MIT
Keywords: mcp,ledger
Requires-Python: >=3.10
Requires-Dist: click>=8.1.8
Requires-Dist: mcp>=1.4.1
